pymailorganizer/__init__.py
pymailorganizer/conftest.py
pymailorganizer/display.py
pymailorganizer/imap.py
pymailorganizer/main.py
pymailorganizer-0.6.2.dist-info/LICENSE
pymailorganizer-0.6.2.dist-info/METADATA
pymailorganizer-0.6.2.dist-info/WHEEL
pymailorganizer-0.6.2.dist-info/entry_points.txt
pymailorganizer-0.6.2.dist-info/top_level.txt
pymailorganizer-0.6.2.dist-info/RECORD
