Metadata-Version: 2.1
Name: pymailorganizer
Version: 0.6.2
Summary: Python command line mail organizer
Home-page: https://github.com/santosgo/pymailorganizer
Author: Gonçalo Brandão Coelho dos Santos
Author-email: goncalo.a.santos@gmail.com
License: MIT
Platform: UNKNOWN
Classifier: License :: OSI Approved :: MIT License
Classifier: Programming Language :: Python :: 3
Classifier: Programming Language :: Python :: 3.7
Requires-Dist: halo
Requires-Dist: matplotlib
Requires-Dist: ntlm-auth
Requires-Dist: numpy
Requires-Dist: pandas
Requires-Dist: pytest
Requires-Dist: requests
Requires-Dist: scipy
Requires-Dist: seaborn
Requires-Dist: tabulate
Requires-Dist: tqdm
Requires-Dist: urllib3
